tembo_pgmq_python/__init__.py
tembo_pgmq_python/async_queue.py
tembo_pgmq_python/decorators.py
tembo_pgmq_python/messages.py
tembo_pgmq_python/queue.py
tembo_pgmq_python-0.10.0.dist-info/METADATA
tembo_pgmq_python-0.10.0.dist-info/WHEEL
tembo_pgmq_python-0.10.0.dist-info/RECORD
