Metadata-Version: 2.1
Name: tembo-pgmq-python
Version: 0.10.0
Summary: Python client for the PGMQ Postgres extension.
License: PostgreSQL
Author: Adam Hendel
Author-email: adam@tembo.io
Requires-Python: >=3.9
Classifier: License :: OSI Approved
Classifier: Programming Language :: Python :: 3
Classifier: Programming Language :: Python :: 3.9
Classifier: Programming Language :: Python :: 3.10
Classifier: Programming Language :: Python :: 3.11
Classifier: Programming Language :: Python :: 3.12
Provides-Extra: async
Requires-Dist: asyncpg (>=0.29.0,<0.30.0) ; extra == "async"
Requires-Dist: orjson (>=3,<4)
Requires-Dist: psycopg[binary,pool] (>=3,<4)
Project-URL: Documentation, https://github.com/tembo-io/pgmq/tree/main/tembo-pgmq-python
Project-URL: Homepage, https://github.com/tembo-io/pgmq
Project-URL: Repository, https://github.com/tembo-io/pgmq/tree/main/tembo-pgmq-python
